{
    "AX": {
        "error": 0.017922786527854763,
        "error_type": "SEM",
        "filter_outliers_dict": {
            "filter_outliers": true,
            "iterations": 1,
            "std_devs": 3,
            "use_iqr_filtering": false,
            "use_standard_deviation_filtering": false
        },
        "fit": "average",
        "fn": 20,
        "include_baseline_error": false,
        "n": 20,
        "outlier_excluded": [],
        "reviewed": true,
        "user_excluded": [],
        "value": -0.028232808411121368
    },
    "CDD": {
        "error": 4.9869380504968117e-05,
        "error_type": "SEM",
        "filter_outliers_dict": {
            "filter_outliers": true,
            "iterations": 1,
            "std_devs": 10,
            "use_iqr_filtering": false,
            "use_standard_deviation_filtering": false
        },
        "fit": "average",
        "fn": 20,
        "include_baseline_error": false,
        "n": 20,
        "outlier_excluded": [],
        "reviewed": true,
        "user_excluded": [],
        "value": 0.0003873816087434534
    },
    "H1": {
        "error": 0.008557704938767875,
        "error_type": "SEM",
        "filter_outliers_dict": {
            "filter_outliers": true,
            "iterations": 1,
            "std_devs": 3,
            "use_iqr_filtering": false,
            "use_standard_deviation_filtering": false
        },
        "fit": "average",
        "fn": 20,
        "include_baseline_error": false,
        "n": 20,
        "outlier_excluded": [],
        "reviewed": true,
        "user_excluded": [],
        "value": 0.026470590359531344
    },
    "H2": {
        "error": 0.023393082911150997,
        "error_type": "SEM",
        "filter_outliers_dict": {
            "filter_outliers": true,
            "iterations": 1,
            "std_devs": 3,
            "use_iqr_filtering": false,
            "use_standard_deviation_filtering": false
        },
        "fit": "average",
        "fn": 20,
        "include_baseline_error": false,
        "n": 20,
        "outlier_excluded": [],
        "reviewed": true,
        "user_excluded": [],
        "value": 0.04088541679375339
    },
    "L1": {
        "error": 0.0038805809740716634,
        "error_type": "SEM",
        "filter_outliers_dict": {
            "filter_outliers": true,
            "iterations": 1,
            "std_devs": 3,
            "use_iqr_filtering": false,
            "use_standard_deviation_filtering": false
        },
        "fit": "average",
        "fn": 20,
        "include_baseline_error": false,
        "n": 20,
        "outlier_excluded": [],
        "reviewed": true,
        "user_excluded": [],
        "value": -0.06534942649304867
    },
    "L2": {
        "error": 0.008573592498543272,
        "error_type": "SEM",
        "filter_outliers_dict": {
            "filter_outliers": true,
            "iterations": 1,
            "std_devs": 2
        },
        "fit": "Average",
        "fn": 20,
        "include_baseline_error": false,
        "n": 20,
        "reviewed": true,
        "value": -0.04505023931300169
    }
}